flaky_tests_detection/__init__.py
flaky_tests_detection/check_flakes.py
flaky_tests_detection-1.3.0.dist-info/LICENSE.md
flaky_tests_detection-1.3.0.dist-info/METADATA
flaky_tests_detection-1.3.0.dist-info/WHEEL
flaky_tests_detection-1.3.0.dist-info/entry_points.txt
flaky_tests_detection-1.3.0.dist-info/top_level.txt
flaky_tests_detection-1.3.0.dist-info/RECORD
