Metadata-Version: 2.1
Name: flaky-tests-detection
Version: 1.3.0
Summary: Github actions plugin to check flakiness of tests by calculating fliprates.
Home-page: https://github.com/F-Secure/flaky-tests-detection
Author: Eero Kauhanen, Matvey Pashkovskiy, Alexey Vyskubov, Tatu Aalto, Joona Oikarinen
Author-email: 
License: Apache License 2.0
Platform: any
Classifier: Programming Language :: Python
Classifier: Programming Language :: Python :: 3
Classifier: Programming Language :: Python :: 3.7
Classifier: Programming Language :: Python :: 3.8
Classifier: Programming Language :: Python :: 3.9
Classifier: Programming Language :: Python :: 3.10
License-File: LICENSE.md
Requires-Dist: pandas
Requires-Dist: junitparser
Requires-Dist: seaborn
Requires-Dist: matplotlib
Provides-Extra: dev
Requires-Dist: pytest ; extra == 'dev'
Requires-Dist: pytest-cov ; extra == 'dev'
Requires-Dist: black ; extra == 'dev'
Requires-Dist: mypy ; extra == 'dev'
Requires-Dist: python-semantic-release ; extra == 'dev'
